antibiotics/__init__.py
antibiotics/py.typed
antibiotics-0.4.dist-info/LICENSE
antibiotics-0.4.dist-info/METADATA
antibiotics-0.4.dist-info/WHEEL
antibiotics-0.4.dist-info/top_level.txt
antibiotics-0.4.dist-info/RECORD
