Metadata-Version: 2.1
Name: antibiotics
Version: 0.4
Summary: a treatment for PANDAS
Home-page: https://github.com/derrickturk/antibiotics
Author: Derrick W. Turk
Author-email: dwt@terminusdatascience.com
Classifier: License :: OSI Approved :: Apache Software License
Classifier: Programming Language :: Python :: 3.10
Classifier: Programming Language :: Python :: 3.11
Classifier: Operating System :: OS Independent
Requires-Python: >=3.10
License-File: LICENSE
